nbdev_intro/__init__.py
nbdev_intro/_nbdev.py
nbdev_intro/advantages.py
nbdev_intro/core.py
nbdev_intro/disadvantages.py
nbdev_intro/nbdev.py
nbdev_intro-0.0.1.dist-info/LICENSE
nbdev_intro-0.0.1.dist-info/METADATA
nbdev_intro-0.0.1.dist-info/WHEEL
nbdev_intro-0.0.1.dist-info/top_level.txt
nbdev_intro-0.0.1.dist-info/RECORD
