Metadata-Version: 2.1
Name: nbdev-intro
Version: 0.0.1
Summary: An introduction to nbdev.
Home-page: https://github.com/hgzech/nbdev_intro/tree/master/
Author: Hilmar Zech
Author-email: hgzech@gmail.com
License: Apache Software License 2.0
Keywords: nbdev introduction
Classifier: Development Status :: 3 - Alpha
Classifier: Intended Audience :: Developers
Classifier: Natural Language :: English
Classifier: Programming Language :: Python :: 3.6
Classifier: Programming Language :: Python :: 3.7
Classifier: Programming Language :: Python :: 3.8
Classifier: Programming Language :: Python :: 3.9
Classifier: Programming Language :: Python :: 3.10
Classifier: License :: OSI Approved :: Apache Software License
Requires-Python: >=3.6
License-File: LICENSE
Requires-Dist: pip
Requires-Dist: packaging
Requires-Dist: pandas
Requires-Dist: seaborn
Requires-Dist: fastparquet
Requires-Dist: matplotlib
Requires-Dist: rpy2
Provides-Extra: dev
